dtsdk/__init__.py
dtsdk/sdk.py
DataToweraiSDK-0.0.1.dist-info/LICENSE
DataToweraiSDK-0.0.1.dist-info/METADATA
DataToweraiSDK-0.0.1.dist-info/WHEEL
DataToweraiSDK-0.0.1.dist-info/top_level.txt
DataToweraiSDK-0.0.1.dist-info/RECORD
