Metadata-Version: 2.1
Name: DataToweraiSDK
Version: 0.0.1
Summary: DataTower.ai SDK
Author-email: LovinJoy <bill@nodetower.com>
Project-URL: Homepage, https://github.com/lovinjoy/datatower.ai-python
Project-URL: Bug Tracker, https://github.com/lovinjoy/datatower.ai-python/issues
Classifier: Programming Language :: Python :: 3
Classifier: License :: OSI Approved :: MIT License
Classifier: Operating System :: OS Independent
Requires-Python: >=2.6
License-File: LICENSE
